{"target": "andreasfertig@@programming-with-cpp20", "extractors": [{"deps": [], "type": "cmake", "libs": []}, {"deps": [], "type": "cmake", "libs": []}, {"deps": [], "type": "cmake", "libs": []}, {"deps": [], "type": "cmake", "libs": []}, {"deps": [], "type": "cmake", "libs": []}, {"deps": [], "type": "cmake", "libs": []}, {"deps": [], "type": "cmake", "libs": []}, {"deps": [], "type": "cmake", "libs": []}, {"deps": [], "type": "cmake", "libs": []}, {"deps": [], "type": "cmake", "libs": []}, {"deps": [], "type": "cmake", "libs": []}, {"deps": [], "type": "cmake", "libs": []}, {"deps": [], "type": "cmake", "libs": []}, {"deps": [], "type": "cmake", "libs": []}, {"deps": [], "type": "cmake", "libs": []}, {"deps": [], "type": "cmake", "libs": []}, {"deps": [], "type": "cmake", "libs": []}, {"deps": [], "type": "cmake", "libs": []}, {"deps": [], "type": "cmake", "libs": []}, {"deps": [], "type": "cmake", "libs": []}, {"deps": [], "type": "cmake", "libs": []}, {"deps": [], "type": "cmake", "libs": []}, {"deps": [], "type": "cmake", "libs": []}, {"deps": [], "type": "cmake", "libs": []}, {"deps": [], "type": "cmake", "libs": []}, {"deps": [], "type": "cmake", "libs": []}, {"deps": [], "type": "cmake", "libs": []}, {"deps": [], "type": "cmake", "libs": []}, {"deps": [], "type": "cmake", "libs": []}, {"deps": [], "type": "cmake", "libs": []}, {"deps": [], "type": "cmake", "libs": []}, {"deps": [], "type": "cmake", "libs": []}, {"deps": [], "type": "cmake", "libs": []}, {"deps": [], "type": "cmake", "libs": []}, {"deps": [], "type": "cmake", "libs": []}, {"deps": [], "type": "cmake", "libs": []}, {"deps": [], "type": "cmake", "libs": []}, {"deps": [], "type": "cmake", "libs": []}, {"deps": [], "type": "cmake", "libs": []}, {"deps": [], "type": "cmake", "libs": []}, {"deps": [], "type": "cmake", "libs": []}, {"deps": [], "type": "cmake", "libs": []}, {"deps": [], "type": "cmake", "libs": []}, {"deps": [], "type": "cmake", "libs": []}, {"deps": [], "type": "cmake", "libs": []}, {"deps": [], "type": "cmake", "libs": []}, {"deps": [], "type": "cmake", "libs": []}, {"deps": [], "type": "cmake", "libs": []}, {"deps": [], "type": "cmake", "libs": []}, {"deps": [], "type": "cmake", "libs": []}, {"deps": [], "type": "cmake", "libs": []}, {"deps": [], "type": "cmake", "libs": []}, {"deps": [], "type": "cmake", "libs": []}, {"deps": [], "type": "cmake", "libs": []}, {"deps": [], "type": "cmake", "libs": []}, {"deps": [], "type": "cmake", "libs": []}, {"deps": [], "type": "cmake", "libs": []}, {"deps": [], "type": "cmake", "libs": []}, {"deps": [], "type": "cmake", "libs": []}, {"deps": [], "type": "cmake", "libs": []}, {"deps": [], "type": "cmake", "libs": []}, {"deps": [], "type": "cmake", "libs": []}, {"deps": [], "type": "cmake", "libs": []}, {"deps": [], "type": "cmake", "libs": []}, {"deps": [], "type": "cmake", "libs": []}, {"deps": [], "type": "cmake", "libs": []}, {"deps": [], "type": "cmake", "libs": []}, {"deps": [], "type": "cmake", "libs": []}, {"deps": [], "type": "cmake", "libs": []}, {"deps": [], "type": "cmake", "libs": []}, {"deps": [], "type": "cmake", "libs": []}, {"deps": [], "type": "cmake", "libs": []}, {"deps": [], "type": "cmake", "libs": []}, {"deps": [], "type": "cmake", "libs": []}, {"deps": [], "type": "cmake", "libs": []}, {"deps": [], "type": "cmake", "libs": []}, {"deps": [], "type": "cmake", "libs": []}, {"deps": [], "type": "cmake", "libs": []}, {"deps": [], "type": "cmake", "libs": []}, {"deps": [], "type": "cmake", "libs": []}, {"deps": [], "type": "cmake", "libs": []}, {"deps": [], "type": "cmake", "libs": []}, {"deps": [], "type": "cmake", "libs": []}, {"deps": [], "type": "cmake", "libs": []}, {"deps": [], "type": "cmake", "libs": []}, {"deps": [], "type": "cmake", "libs": []}, {"deps": [], "type": "cmake", "libs": []}, {"deps": [], "type": "cmake", "libs": []}, {"deps": [], "type": "cmake", "libs": []}, {"deps": [], "type": "cmake", "libs": []}, {"deps": [], "type": "cmake", "libs": []}, {"deps": [], "type": "cmake", "libs": []}, {"deps": [], "type": "cmake", "libs": []}, {"deps": [], "type": "cmake", "libs": []}, {"deps": [], "type": "cmake", "libs": []}, {"deps": [], "type": "cmake", "libs": []}, {"deps": [], "type": "cmake", "libs": []}, {"deps": [], "type": "cmake", "libs": []}, {"deps": [], "type": "cmake", "libs": []}, {"deps": [], "type": "cmake", "libs": []}, {"deps": [], "type": "cmake", "libs": []}, {"deps": [], "type": "cmake", "libs": []}, {"deps": [], "type": "cmake", "libs": []}, {"deps": [], "type": "cmake", "libs": []}, {"deps": [], "type": "cmake", "libs": []}, {"deps": [], "type": "cmake", "libs": []}, {"deps": [], "type": "cmake", "libs": []}, {"deps": [], "type": "cmake", "libs": []}, {"deps": [], "type": "cmake", "libs": []}, {"deps": [], "type": "cmake", "libs": []}, {"deps": [], "type": "cmake", "libs": []}, {"deps": [], "type": "cmake", "libs": []}, {"deps": [], "type": "cmake", "libs": []}, {"deps": [], "type": "cmake", "libs": []}, {"deps": [], "type": "cmake", "libs": []}, {"deps": [], "type": "cmake", "libs": []}, {"deps": [], "type": "cmake", "libs": []}, {"deps": [], "type": "cmake", "libs": []}, {"deps": [], "type": "cmake", "libs": []}, {"deps": [], "type": "cmake", "libs": []}, {"deps": [], "type": "cmake", "libs": []}, {"deps": [], "type": "cmake", "libs": []}, {"deps": [], "type": "cmake", "libs": []}, {"deps": [], "type": "cmake", "libs": []}, {"deps": [], "type": "cmake", "libs": []}, {"deps": [], "type": "cmake", "libs": []}, {"deps": [], "type": "cmake", "libs": []}, {"deps": [], "type": "cmake", "libs": []}, {"deps": [], "type": "cmake", "libs": []}, {"deps": [], "type": "cmake", "libs": []}, {"deps": [], "type": "cmake", "libs": []}, {"deps": [], "type": "cmake", "libs": []}, {"deps": [], "type": "cmake", "libs": []}, {"deps": [], "type": "cmake", "libs": []}, {"deps": [], "type": "cmake", "libs": []}, {"deps": [], "type": "cmake", "libs": []}, {"deps": [], "type": "cmake", "libs": []}, {"deps": [], "type": "cmake", "libs": []}, {"deps": [], "type": "cmake", "libs": []}, {"deps": [], "type": "cmake", "libs": []}, {"deps": [], "type": "cmake", "libs": []}, {"deps": [], "type": "cmake", "libs": []}, {"deps": [], "type": "cmake", "libs": []}, {"deps": [], "type": "cmake", "libs": []}, {"deps": [], "type": "cmake", "libs": []}, {"deps": [], "type": "cmake", "libs": []}, {"deps": [], "type": "cmake", "libs": []}, {"deps": [], "type": "cmake", "libs": []}, {"deps": [], "type": "cmake", "libs": []}, {"deps": [], "type": "cmake", "libs": []}, {"deps": [], "type": "cmake", "libs": []}, {"deps": [], "type": "cmake", "libs": []}, {"deps": [], "type": "cmake", "libs": []}, {"deps": [], "type": "cmake", "libs": []}, {"deps": [], "type": "cmake", "libs": []}, {"deps": [], "type": "cmake", "libs": []}, {"deps": [], "type": "cmake", "libs": []}, {"deps": [], "type": "cmake", "libs": []}, {"deps": [], "type": "cmake", "libs": []}, {"deps": [], "type": "cmake", "libs": []}, {"deps": [], "type": "cmake", "libs": []}, {"deps": [], "type": "cmake", "libs": []}, {"deps": [], "type": "cmake", "libs": []}, {"deps": [], "type": "cmake", "libs": []}, {"deps": [], "type": "cmake", "libs": []}, {"deps": [], "type": "cmake", "libs": []}, {"deps": [], "type": "cmake", "libs": []}, {"deps": [], "type": "cmake", "libs": []}, {"deps": [], "type": "cmake", "libs": []}, {"deps": [], "type": "cmake", "libs": []}, {"deps": [], "type": "cmake", "libs": []}, {"deps": [], "type": "cmake", "libs": []}, {"deps": [], "type": "cmake", "libs": []}, {"deps": [], "type": "cmake", "libs": []}, {"deps": [], "type": "cmake", "libs": []}, {"deps": [], "type": "cmake", "libs": []}, {"deps": [], "type": "cmake", "libs": []}, {"deps": [], "type": "cmake", "libs": []}, {"deps": [], "type": "cmake", "libs": []}, {"deps": [], "type": "cmake", "libs": []}, {"deps": [], "type": "cmake", "libs": []}, {"deps": [], "type": "cmake", "libs": []}, {"deps": [], "type": "cmake", "libs": []}, {"deps": [], "type": "cmake", "libs": []}, {"deps": [], "type": "cmake", "libs": []}, {"deps": [], "type": "cmake", "libs": []}, {"deps": [], "type": "cmake", "libs": []}, {"deps": [], "type": "cmake", "libs": []}, {"deps": [], "type": "cmake", "libs": []}, {"deps": [], "type": "cmake", "libs": []}, {"deps": [], "type": "cmake", "libs": []}, {"deps": [], "type": "cmake", "libs": []}, {"deps": [], "type": "cmake", "libs": []}, {"deps": [], "type": "cmake", "libs": []}, {"deps": [], "type": "cmake", "libs": []}, {"deps": [], "type": "cmake", "libs": []}, {"deps": [], "type": "cmake", "libs": []}, {"deps": [], "type": "cmake", "libs": []}, {"deps": [], "type": "cmake", "libs": []}, {"deps": [], "type": "cmake", "libs": []}, {"deps": [], "type": "cmake", "libs": []}, {"deps": [], "type": "cmake", "libs": []}, {"deps": [], "type": "cmake", "libs": []}, {"deps": [], "type": "cmake", "libs": []}, {"deps": [], "type": "cmake", "libs": []}, {"deps": [], "type": "cmake", "libs": []}]}