{"target": "ANYbotics@@point_cloud_io", "extractors": [{"deps": [{"depname": "catkin", "version": null, "version_op": null, "unified_name": "catkin", "extractor_type": "cmake", "context": "find_package(catkin required\n  components\n    ${catkin_package_dependencies}\n)", "confidence": "High"}, {"depname": "cmake_clang_tools", "version": null, "version_op": null, "unified_name": "cmake_clang_tools", "extractor_type": "cmake", "context": "find_package(cmake_clang_tools quiet)", "confidence": "High"}, {"depname": "cmake_code_coverage", "version": null, "version_op": null, "unified_name": "cmake_code_coverage", "extractor_type": "cmake", "context": "find_package(cmake_code_coverage quiet)", "confidence": "High"}, {"depname": "point_cloud_io", "version": null, "version_op": null, "unified_name": "point_cloud_io", "extractor_type": "cmake", "context": "project(point_cloud_io)", "confidence": ""}], "type": "cmake", "libs": []}]}