{"target": "cruppstahl@@upscaledb", "extractors": [{"deps": [], "type": "gitsubmod"}, {"deps": [{"depname": "upscaledb", "version": "2.2.1", "version_op": null, "unified_name": "upscaledb", "extractor_type": "autoconf", "context": "AC_INIT([upscaledb], [2.2.1], [https://upscaledb.com])", "confidence": ""}, {"depname": "tcmalloc_minimal", "version": null, "version_op": null, "unified_name": "tcmalloc_minimal", "extractor_type": "autoconf", "context": "cruppstahl@@upscaledb/configure.ac", "confidence": "High"}, {"depname": "crypto", "version": null, "version_op": null, "unified_name": "crypto", "extractor_type": "autoconf", "context": "cruppstahl@@upscaledb/configure.ac", "confidence": "High"}, {"depname": "db", "version": null, "version_op": null, "unified_name": "db", "extractor_type": "autoconf", "context": "cruppstahl@@upscaledb/configure.ac", "confidence": "High"}], "type": "autoconf"}, {"deps": [], "type": "make"}, {"deps": [], "type": "ms"}, {"deps": [], "type": "ms"}, {"deps": [{"depname": "Iphlpapi", "version": null, "version_op": null, "unified_name": "iphlpapi", "extractor_type": "ms", "context": "cruppstahl@@upscaledb/win32/msvc2013/server_dll.vcxproj", "confidence": "High"}, {"depname": "Psapi", "version": null, "version_op": null, "unified_name": "psapi", "extractor_type": "ms", "context": "cruppstahl@@upscaledb/win32/msvc2013/server_dll.vcxproj", "confidence": "High"}, {"depname": "kernel32", "version": null, "version_op": null, "unified_name": "kernel32", "extractor_type": "ms", "context": "cruppstahl@@upscaledb/win32/msvc2013/server_dll.vcxproj", "confidence": "High"}, {"depname": "user32", "version": null, "version_op": null, "unified_name": "user32", "extractor_type": "ms", "context": "cruppstahl@@upscaledb/win32/msvc2013/server_dll.vcxproj", "confidence": "High"}, {"depname": "gdi32", "version": null, "version_op": null, "unified_name": "gdi32", "extractor_type": "ms", "context": "cruppstahl@@upscaledb/win32/msvc2013/server_dll.vcxproj", "confidence": "High"}, {"depname": "winspool", "version": null, "version_op": null, "unified_name": "winspool", "extractor_type": "ms", "context": "cruppstahl@@upscaledb/win32/msvc2013/server_dll.vcxproj", "confidence": "High"}, {"depname": "comdlg32", "version": null, "version_op": null, "unified_name": "comdlg32", "extractor_type": "ms", "context": "cruppstahl@@upscaledb/win32/msvc2013/server_dll.vcxproj", "confidence": "High"}, {"depname": "advapi32", "version": null, "version_op": null, "unified_name": "advapi32", "extractor_type": "ms", "context": "cruppstahl@@upscaledb/win32/msvc2013/server_dll.vcxproj", "confidence": "High"}, {"depname": "shell32", "version": null, "version_op": null, "unified_name": "shell32", "extractor_type": "ms", "context": "cruppstahl@@upscaledb/win32/msvc2013/server_dll.vcxproj", "confidence": "High"}, {"depname": "ole32", "version": null, "version_op": null, "unified_name": "ole32", "extractor_type": "ms", "context": "cruppstahl@@upscaledb/win32/msvc2013/server_dll.vcxproj", "confidence": "High"}, {"depname": "oleaut32", "version": null, "version_op": null, "unified_name": "oleaut32", "extractor_type": "ms", "context": "cruppstahl@@upscaledb/win32/msvc2013/server_dll.vcxproj", "confidence": "High"}, {"depname": "uuid", "version": null, "version_op": null, "unified_name": "uuid", "extractor_type": "ms", "context": "cruppstahl@@upscaledb/win32/msvc2013/server_dll.vcxproj", "confidence": "High"}, {"depname": "odbc32", "version": null, "version_op": null, "unified_name": "odbc32", "extractor_type": "ms", "context": "cruppstahl@@upscaledb/win32/msvc2013/server_dll.vcxproj", "confidence": "High"}, {"depname": "odbccp32", "version": null, "version_op": null, "unified_name": "odbccp32", "extractor_type": "ms", "context": "cruppstahl@@upscaledb/win32/msvc2013/server_dll.vcxproj", "confidence": "High"}, {"depname": "Iphlpapi", "version": null, "version_op": null, "unified_name": "iphlpapi", "extractor_type": "ms", "context": "cruppstahl@@upscaledb/win32/msvc2013/server_dll.vcxproj", "confidence": "High"}, {"depname": "psapi", "version": null, "version_op": null, "unified_name": "psapi", "extractor_type": "ms", "context": "cruppstahl@@upscaledb/win32/msvc2013/server_dll.vcxproj", "confidence": "High"}, {"depname": "kernel32", "version": null, "version_op": null, "unified_name": "kernel32", "extractor_type": "ms", "context": "cruppstahl@@upscaledb/win32/msvc2013/server_dll.vcxproj", "confidence": "High"}, {"depname": "user32", "version": null, "version_op": null, "unified_name": "user32", "extractor_type": "ms", "context": "cruppstahl@@upscaledb/win32/msvc2013/server_dll.vcxproj", "confidence": "High"}, {"depname": "gdi32", "version": null, "version_op": null, "unified_name": "gdi32", "extractor_type": "ms", "context": "cruppstahl@@upscaledb/win32/msvc2013/server_dll.vcxproj", "confidence": "High"}, {"depname": "winspool", "version": null, "version_op": null, "unified_name": "winspool", "extractor_type": "ms", "context": "cruppstahl@@upscaledb/win32/msvc2013/server_dll.vcxproj", "confidence": "High"}, {"depname": "comdlg32", "version": null, "version_op": null, "unified_name": "comdlg32", "extractor_type": "ms", "context": "cruppstahl@@upscaledb/win32/msvc2013/server_dll.vcxproj", "confidence": "High"}, {"depname": "advapi32", "version": null, "version_op": null, "unified_name": "advapi32", "extractor_type": "ms", "context": "cruppstahl@@upscaledb/win32/msvc2013/server_dll.vcxproj", "confidence": "High"}, {"depname": "shell32", "version": null, "version_op": null, "unified_name": "shell32", "extractor_type": "ms", "context": "cruppstahl@@upscaledb/win32/msvc2013/server_dll.vcxproj", "confidence": "High"}, {"depname": "ole32", "version": null, "version_op": null, "unified_name": "ole32", "extractor_type": "ms", "context": "cruppstahl@@upscaledb/win32/msvc2013/server_dll.vcxproj", "confidence": "High"}, {"depname": "oleaut32", "version": null, "version_op": null, "unified_name": "oleaut32", "extractor_type": "ms", "context": "cruppstahl@@upscaledb/win32/msvc2013/server_dll.vcxproj", "confidence": "High"}, {"depname": "uuid", "version": null, "version_op": null, "unified_name": "uuid", "extractor_type": "ms", "context": "cruppstahl@@upscaledb/win32/msvc2013/server_dll.vcxproj", "confidence": "High"}, {"depname": "odbc32", "version": null, "version_op": null, "unified_name": "odbc32", "extractor_type": "ms", "context": "cruppstahl@@upscaledb/win32/msvc2013/server_dll.vcxproj", "confidence": "High"}, {"depname": "odbccp32", "version": null, "version_op": null, "unified_name": "odbccp32", "extractor_type": "ms", "context": "cruppstahl@@upscaledb/win32/msvc2013/server_dll.vcxproj", "confidence": "High"}, {"depname": "Psapi", "version": null, "version_op": null, "unified_name": "psapi", "extractor_type": "ms", "context": "cruppstahl@@upscaledb/win32/msvc2013/server_dll.vcxproj", "confidence": "High"}, {"depname": "Iphlpapi", "version": null, "version_op": null, "unified_name": "iphlpapi", "extractor_type": "ms", "context": "cruppstahl@@upscaledb/win32/msvc2013/server_dll.vcxproj", "confidence": "High"}, {"depname": "Iphlpapi", "version": null, "version_op": null, "unified_name": "iphlpapi", "extractor_type": "ms", "context": "cruppstahl@@upscaledb/win32/msvc2013/server_dll.vcxproj", "confidence": "High"}, {"depname": "psapi", "version": null, "version_op": null, "unified_name": "psapi", "extractor_type": "ms", "context": "cruppstahl@@upscaledb/win32/msvc2013/server_dll.vcxproj", "confidence": "High"}], "type": "ms"}, {"deps": [{"depname": "", "version": null, "version_op": null, "unified_name": "", "extractor_type": "ms", "context": "cruppstahl@@upscaledb/win32/msvc2013/protobuf.vcxproj", "confidence": "High"}, {"depname": "", "version": null, "version_op": null, "unified_name": "", "extractor_type": "ms", "context": "cruppstahl@@upscaledb/win32/msvc2013/protobuf.vcxproj", "confidence": "High"}, {"depname": "", "version": null, "version_op": null, "unified_name": "", "extractor_type": "ms", "context": "cruppstahl@@upscaledb/win32/msvc2013/protobuf.vcxproj", "confidence": "High"}, {"depname": "", "version": null, "version_op": null, "unified_name": "", "extractor_type": "ms", "context": "cruppstahl@@upscaledb/win32/msvc2013/protobuf.vcxproj", "confidence": "High"}], "type": "ms"}, {"deps": [], "type": "ms"}, {"deps": [], "type": "ms"}, {"deps": [], "type": "ms"}, {"deps": [], "type": "ms"}, {"deps": [], "type": "ms"}, {"deps": [], "type": "ms"}, {"deps": [{"depname": "", "version": null, "version_op": null, "unified_name": "", "extractor_type": "ms", "context": "cruppstahl@@upscaledb/win32/msvc2013/dll.vcxproj", "confidence": "High"}, {"depname": "", "version": null, "version_op": null, "unified_name": "", "extractor_type": "ms", "context": "cruppstahl@@upscaledb/win32/msvc2013/dll.vcxproj", "confidence": "High"}, {"depname": "", "version": null, "version_op": null, "unified_name": "", "extractor_type": "ms", "context": "cruppstahl@@upscaledb/win32/msvc2013/dll.vcxproj", "confidence": "High"}, {"depname": "tmp\\libvbyte_debug\\libvbyte", "version": null, "version_op": null, "unified_name": "tmp\\libvbyte_debug\\libvbyte", "extractor_type": "ms", "context": "cruppstahl@@upscaledb/win32/msvc2013/dll.vcxproj", "confidence": "High"}, {"depname": "tmp\\libfor_debug\\libfor", "version": null, "version_op": null, "unified_name": "tmp\\libfor_debug\\libfor", "extractor_type": "ms", "context": "cruppstahl@@upscaledb/win32/msvc2013/dll.vcxproj", "confidence": "High"}, {"depname": "libboost_thread-vc120-mt-gd-1_58", "version": null, "version_op": null, "unified_name": "boost_thread-vc120-mt-gd-1_58", "extractor_type": "ms", "context": "cruppstahl@@upscaledb/win32/msvc2013/dll.vcxproj", "confidence": "High"}, {"depname": "ws2_32", "version": null, "version_op": null, "unified_name": "ws2_32", "extractor_type": "ms", "context": "cruppstahl@@upscaledb/win32/msvc2013/dll.vcxproj", "confidence": "High"}, {"depname": "%(AdditionalDependencies)", "version": null, "version_op": null, "unified_name": "%(additionaldependencies)", "extractor_type": "ms", "context": "cruppstahl@@upscaledb/win32/msvc2013/dll.vcxproj", "confidence": "High"}, {"depname": "Wldap32", "version": null, "version_op": null, "unified_name": "wldap32", "extractor_type": "ms", "context": "cruppstahl@@upscaledb/win32/msvc2013/dll.vcxproj", "confidence": "High"}, {"depname": "", "version": null, "version_op": null, "unified_name": "", "extractor_type": "ms", "context": "cruppstahl@@upscaledb/win32/msvc2013/dll.vcxproj", "confidence": "High"}, {"depname": "", "version": null, "version_op": null, "unified_name": "", "extractor_type": "ms", "context": "cruppstahl@@upscaledb/win32/msvc2013/dll.vcxproj", "confidence": "High"}, {"depname": "", "version": null, "version_op": null, "unified_name": "", "extractor_type": "ms", "context": "cruppstahl@@upscaledb/win32/msvc2013/dll.vcxproj", "confidence": "High"}, {"depname": "libboost_thread-vc120-mt-gd-1_58", "version": null, "version_op": null, "unified_name": "boost_thread-vc120-mt-gd-1_58", "extractor_type": "ms", "context": "cruppstahl@@upscaledb/win32/msvc2013/dll.vcxproj", "confidence": "High"}, {"depname": "tmp\\libvbyte_debug_x64\\libvbyte", "version": null, "version_op": null, "unified_name": "tmp\\libvbyte_debug_x64\\libvbyte", "extractor_type": "ms", "context": "cruppstahl@@upscaledb/win32/msvc2013/dll.vcxproj", "confidence": "High"}, {"depname": "tmp\\libfor_debug_x64\\libfor", "version": null, "version_op": null, "unified_name": "tmp\\libfor_debug_x64\\libfor", "extractor_type": "ms", "context": "cruppstahl@@upscaledb/win32/msvc2013/dll.vcxproj", "confidence": "High"}, {"depname": "ws2_32", "version": null, "version_op": null, "unified_name": "ws2_32", "extractor_type": "ms", "context": "cruppstahl@@upscaledb/win32/msvc2013/dll.vcxproj", "confidence": "High"}, {"depname": "%(AdditionalDependencies)", "version": null, "version_op": null, "unified_name": "%(additionaldependencies)", "extractor_type": "ms", "context": "cruppstahl@@upscaledb/win32/msvc2013/dll.vcxproj", "confidence": "High"}, {"depname": "Wldap32", "version": null, "version_op": null, "unified_name": "wldap32", "extractor_type": "ms", "context": "cruppstahl@@upscaledb/win32/msvc2013/dll.vcxproj", "confidence": "High"}, {"depname": "", "version": null, "version_op": null, "unified_name": "", "extractor_type": "ms", "context": "cruppstahl@@upscaledb/win32/msvc2013/dll.vcxproj", "confidence": "High"}, {"depname": "", "version": null, "version_op": null, "unified_name": "", "extractor_type": "ms", "context": "cruppstahl@@upscaledb/win32/msvc2013/dll.vcxproj", "confidence": "High"}, {"depname": "", "version": null, "version_op": null, "unified_name": "", "extractor_type": "ms", "context": "cruppstahl@@upscaledb/win32/msvc2013/dll.vcxproj", "confidence": "High"}, {"depname": "libboost_thread-vc120-mt-1_58", "version": null, "version_op": null, "unified_name": "boost_thread-vc120-mt-1_58", "extractor_type": "ms", "context": "cruppstahl@@upscaledb/win32/msvc2013/dll.vcxproj", "confidence": "High"}, {"depname": "tmp\\libvbyte\\libvbyte", "version": null, "version_op": null, "unified_name": "tmp\\libvbyte\\libvbyte", "extractor_type": "ms", "context": "cruppstahl@@upscaledb/win32/msvc2013/dll.vcxproj", "confidence": "High"}, {"depname": "tmp\\libfor\\libfor", "version": null, "version_op": null, "unified_name": "tmp\\libfor\\libfor", "extractor_type": "ms", "context": "cruppstahl@@upscaledb/win32/msvc2013/dll.vcxproj", "confidence": "High"}, {"depname": "ws2_32", "version": null, "version_op": null, "unified_name": "ws2_32", "extractor_type": "ms", "context": "cruppstahl@@upscaledb/win32/msvc2013/dll.vcxproj", "confidence": "High"}, {"depname": "%(AdditionalDependencies)", "version": null, "version_op": null, "unified_name": "%(additionaldependencies)", "extractor_type": "ms", "context": "cruppstahl@@upscaledb/win32/msvc2013/dll.vcxproj", "confidence": "High"}, {"depname": "Wldap32", "version": null, "version_op": null, "unified_name": "wldap32", "extractor_type": "ms", "context": "cruppstahl@@upscaledb/win32/msvc2013/dll.vcxproj", "confidence": "High"}, {"depname": "", "version": null, "version_op": null, "unified_name": "", "extractor_type": "ms", "context": "cruppstahl@@upscaledb/win32/msvc2013/dll.vcxproj", "confidence": "High"}, {"depname": "", "version": null, "version_op": null, "unified_name": "", "extractor_type": "ms", "context": "cruppstahl@@upscaledb/win32/msvc2013/dll.vcxproj", "confidence": "High"}, {"depname": "", "version": null, "version_op": null, "unified_name": "", "extractor_type": "ms", "context": "cruppstahl@@upscaledb/win32/msvc2013/dll.vcxproj", "confidence": "High"}, {"depname": "libboost_thread-vc120-mt-1_58", "version": null, "version_op": null, "unified_name": "boost_thread-vc120-mt-1_58", "extractor_type": "ms", "context": "cruppstahl@@upscaledb/win32/msvc2013/dll.vcxproj", "confidence": "High"}, {"depname": "tmp\\libvbyte_x64\\libvbyte", "version": null, "version_op": null, "unified_name": "tmp\\libvbyte_x64\\libvbyte", "extractor_type": "ms", "context": "cruppstahl@@upscaledb/win32/msvc2013/dll.vcxproj", "confidence": "High"}, {"depname": "tmp\\libfor_x64\\libfor", "version": null, "version_op": null, "unified_name": "tmp\\libfor_x64\\libfor", "extractor_type": "ms", "context": "cruppstahl@@upscaledb/win32/msvc2013/dll.vcxproj", "confidence": "High"}, {"depname": "ws2_32", "version": null, "version_op": null, "unified_name": "ws2_32", "extractor_type": "ms", "context": "cruppstahl@@upscaledb/win32/msvc2013/dll.vcxproj", "confidence": "High"}, {"depname": "%(AdditionalDependencies)", "version": null, "version_op": null, "unified_name": "%(additionaldependencies)", "extractor_type": "ms", "context": "cruppstahl@@upscaledb/win32/msvc2013/dll.vcxproj", "confidence": "High"}, {"depname": "Wldap32", "version": null, "version_op": null, "unified_name": "wldap32", "extractor_type": "ms", "context": "cruppstahl@@upscaledb/win32/msvc2013/dll.vcxproj", "confidence": "High"}], "type": "ms"}, {"deps": [], "type": "ms"}, {"deps": [], "type": "ms"}, {"deps": [{"depname": "ws2_32", "version": null, "version_op": null, "unified_name": "ws2_32", "extractor_type": "ms", "context": "cruppstahl@@upscaledb/win32/msvc2013/server_lib.vcxproj", "confidence": "High"}, {"depname": "%(AdditionalDependencies)", "version": null, "version_op": null, "unified_name": "%(additionaldependencies)", "extractor_type": "ms", "context": "cruppstahl@@upscaledb/win32/msvc2013/server_lib.vcxproj", "confidence": "High"}, {"depname": "", "version": null, "version_op": null, "unified_name": "", "extractor_type": "ms", "context": "cruppstahl@@upscaledb/win32/msvc2013/server_lib.vcxproj", "confidence": "High"}, {"depname": "Iphlpapi", "version": null, "version_op": null, "unified_name": "iphlpapi", "extractor_type": "ms", "context": "cruppstahl@@upscaledb/win32/msvc2013/server_lib.vcxproj", "confidence": "High"}, {"depname": "Psapi", "version": null, "version_op": null, "unified_name": "psapi", "extractor_type": "ms", "context": "cruppstahl@@upscaledb/win32/msvc2013/server_lib.vcxproj", "confidence": "High"}, {"depname": "ws2_32", "version": null, "version_op": null, "unified_name": "ws2_32", "extractor_type": "ms", "context": "cruppstahl@@upscaledb/win32/msvc2013/server_lib.vcxproj", "confidence": "High"}, {"depname": "Iphlpapi", "version": null, "version_op": null, "unified_name": "iphlpapi", "extractor_type": "ms", "context": "cruppstahl@@upscaledb/win32/msvc2013/server_lib.vcxproj", "confidence": "High"}, {"depname": "psapi", "version": null, "version_op": null, "unified_name": "psapi", "extractor_type": "ms", "context": "cruppstahl@@upscaledb/win32/msvc2013/server_lib.vcxproj", "confidence": "High"}, {"depname": "ws2_32", "version": null, "version_op": null, "unified_name": "ws2_32", "extractor_type": "ms", "context": "cruppstahl@@upscaledb/win32/msvc2013/server_lib.vcxproj", "confidence": "High"}, {"depname": "%(AdditionalDependencies)", "version": null, "version_op": null, "unified_name": "%(additionaldependencies)", "extractor_type": "ms", "context": "cruppstahl@@upscaledb/win32/msvc2013/server_lib.vcxproj", "confidence": "High"}, {"depname": "Iphlpapi", "version": null, "version_op": null, "unified_name": "iphlpapi", "extractor_type": "ms", "context": "cruppstahl@@upscaledb/win32/msvc2013/server_lib.vcxproj", "confidence": "High"}, {"depname": "Psapi", "version": null, "version_op": null, "unified_name": "psapi", "extractor_type": "ms", "context": "cruppstahl@@upscaledb/win32/msvc2013/server_lib.vcxproj", "confidence": "High"}, {"depname": "ws2_32", "version": null, "version_op": null, "unified_name": "ws2_32", "extractor_type": "ms", "context": "cruppstahl@@upscaledb/win32/msvc2013/server_lib.vcxproj", "confidence": "High"}, {"depname": "Iphlpapi", "version": null, "version_op": null, "unified_name": "iphlpapi", "extractor_type": "ms", "context": "cruppstahl@@upscaledb/win32/msvc2013/server_lib.vcxproj", "confidence": "High"}, {"depname": "psapi", "version": null, "version_op": null, "unified_name": "psapi", "extractor_type": "ms", "context": "cruppstahl@@upscaledb/win32/msvc2013/server_lib.vcxproj", "confidence": "High"}], "type": "ms"}, {"deps": [{"depname": "", "version": null, "version_op": null, "unified_name": "", "extractor_type": "ms", "context": "cruppstahl@@upscaledb/win32/msvc2013/ups_export.vcxproj", "confidence": "High"}, {"depname": "", "version": null, "version_op": null, "unified_name": "", "extractor_type": "ms", "context": "cruppstahl@@upscaledb/win32/msvc2013/ups_export.vcxproj", "confidence": "High"}, {"depname": "", "version": null, "version_op": null, "unified_name": "", "extractor_type": "ms", "context": "cruppstahl@@upscaledb/win32/msvc2013/ups_export.vcxproj", "confidence": "High"}, {"depname": "", "version": null, "version_op": null, "unified_name": "", "extractor_type": "ms", "context": "cruppstahl@@upscaledb/win32/msvc2013/ups_export.vcxproj", "confidence": "High"}], "type": "ms"}, {"deps": [], "type": "ms"}, {"deps": [], "type": "ms"}, {"deps": [], "type": "ms"}, {"deps": [], "type": "ms"}, {"deps": [], "type": "ms"}, {"deps": [], "type": "ms"}, {"deps": [], "type": "ms"}, {"deps": [], "type": "ms"}, {"deps": [], "type": "ms"}, {"deps": [], "type": "ms"}, {"deps": [{"depname": "", "version": null, "version_op": null, "unified_name": "", "extractor_type": "ms", "context": "cruppstahl@@upscaledb/win32/msvc2013/lib.vcxproj", "confidence": "High"}, {"depname": "", "version": null, "version_op": null, "unified_name": "", "extractor_type": "ms", "context": "cruppstahl@@upscaledb/win32/msvc2013/lib.vcxproj", "confidence": "High"}, {"depname": "libboost_thread-vc120-mt-gd-1_58", "version": null, "version_op": null, "unified_name": "boost_thread-vc120-mt-gd-1_58", "extractor_type": "ms", "context": "cruppstahl@@upscaledb/win32/msvc2013/lib.vcxproj", "confidence": "High"}, {"depname": "", "version": null, "version_op": null, "unified_name": "", "extractor_type": "ms", "context": "cruppstahl@@upscaledb/win32/msvc2013/lib.vcxproj", "confidence": "High"}, {"depname": "tmp\\libvbyte_debug\\libvbyte", "version": null, "version_op": null, "unified_name": "tmp\\libvbyte_debug\\libvbyte", "extractor_type": "ms", "context": "cruppstahl@@upscaledb/win32/msvc2013/lib.vcxproj", "confidence": "High"}, {"depname": "tmp\\libfor_debug\\libfor", "version": null, "version_op": null, "unified_name": "tmp\\libfor_debug\\libfor", "extractor_type": "ms", "context": "cruppstahl@@upscaledb/win32/msvc2013/lib.vcxproj", "confidence": "High"}, {"depname": "ws2_32", "version": null, "version_op": null, "unified_name": "ws2_32", "extractor_type": "ms", "context": "cruppstahl@@upscaledb/win32/msvc2013/lib.vcxproj", "confidence": "High"}, {"depname": "%(AdditionalDependencies)", "version": null, "version_op": null, "unified_name": "%(additionaldependencies)", "extractor_type": "ms", "context": "cruppstahl@@upscaledb/win32/msvc2013/lib.vcxproj", "confidence": "High"}, {"depname": "Wldap32", "version": null, "version_op": null, "unified_name": "wldap32", "extractor_type": "ms", "context": "cruppstahl@@upscaledb/win32/msvc2013/lib.vcxproj", "confidence": "High"}, {"depname": "", "version": null, "version_op": null, "unified_name": "", "extractor_type": "ms", "context": "cruppstahl@@upscaledb/win32/msvc2013/lib.vcxproj", "confidence": "High"}, {"depname": "", "version": null, "version_op": null, "unified_name": "", "extractor_type": "ms", "context": "cruppstahl@@upscaledb/win32/msvc2013/lib.vcxproj", "confidence": "High"}, {"depname": "", "version": null, "version_op": null, "unified_name": "", "extractor_type": "ms", "context": "cruppstahl@@upscaledb/win32/msvc2013/lib.vcxproj", "confidence": "High"}, {"depname": "", "version": null, "version_op": null, "unified_name": "", "extractor_type": "ms", "context": "cruppstahl@@upscaledb/win32/msvc2013/lib.vcxproj", "confidence": "High"}, {"depname": "tmp\\libvbyte_debug_x64\\libvbyte", "version": null, "version_op": null, "unified_name": "tmp\\libvbyte_debug_x64\\libvbyte", "extractor_type": "ms", "context": "cruppstahl@@upscaledb/win32/msvc2013/lib.vcxproj", "confidence": "High"}, {"depname": "tmp\\libfor_debug_x64\\libfor", "version": null, "version_op": null, "unified_name": "tmp\\libfor_debug_x64\\libfor", "extractor_type": "ms", "context": "cruppstahl@@upscaledb/win32/msvc2013/lib.vcxproj", "confidence": "High"}, {"depname": "ws2_32", "version": null, "version_op": null, "unified_name": "ws2_32", "extractor_type": "ms", "context": "cruppstahl@@upscaledb/win32/msvc2013/lib.vcxproj", "confidence": "High"}, {"depname": "%(AdditionalDependencies)", "version": null, "version_op": null, "unified_name": "%(additionaldependencies)", "extractor_type": "ms", "context": "cruppstahl@@upscaledb/win32/msvc2013/lib.vcxproj", "confidence": "High"}, {"depname": "Wldap32", "version": null, "version_op": null, "unified_name": "wldap32", "extractor_type": "ms", "context": "cruppstahl@@upscaledb/win32/msvc2013/lib.vcxproj", "confidence": "High"}, {"depname": "", "version": null, "version_op": null, "unified_name": "", "extractor_type": "ms", "context": "cruppstahl@@upscaledb/win32/msvc2013/lib.vcxproj", "confidence": "High"}, {"depname": "", "version": null, "version_op": null, "unified_name": "", "extractor_type": "ms", "context": "cruppstahl@@upscaledb/win32/msvc2013/lib.vcxproj", "confidence": "High"}, {"depname": "", "version": null, "version_op": null, "unified_name": "", "extractor_type": "ms", "context": "cruppstahl@@upscaledb/win32/msvc2013/lib.vcxproj", "confidence": "High"}, {"depname": "libboost_thread-vc120-mt-1_58", "version": null, "version_op": null, "unified_name": "boost_thread-vc120-mt-1_58", "extractor_type": "ms", "context": "cruppstahl@@upscaledb/win32/msvc2013/lib.vcxproj", "confidence": "High"}, {"depname": "tmp\\libvbyte\\libvbyte", "version": null, "version_op": null, "unified_name": "tmp\\libvbyte\\libvbyte", "extractor_type": "ms", "context": "cruppstahl@@upscaledb/win32/msvc2013/lib.vcxproj", "confidence": "High"}, {"depname": "tmp\\libfor\\libfor", "version": null, "version_op": null, "unified_name": "tmp\\libfor\\libfor", "extractor_type": "ms", "context": "cruppstahl@@upscaledb/win32/msvc2013/lib.vcxproj", "confidence": "High"}, {"depname": "ws2_32", "version": null, "version_op": null, "unified_name": "ws2_32", "extractor_type": "ms", "context": "cruppstahl@@upscaledb/win32/msvc2013/lib.vcxproj", "confidence": "High"}, {"depname": "%(AdditionalDependencies)", "version": null, "version_op": null, "unified_name": "%(additionaldependencies)", "extractor_type": "ms", "context": "cruppstahl@@upscaledb/win32/msvc2013/lib.vcxproj", "confidence": "High"}, {"depname": "Wldap32", "version": null, "version_op": null, "unified_name": "wldap32", "extractor_type": "ms", "context": "cruppstahl@@upscaledb/win32/msvc2013/lib.vcxproj", "confidence": "High"}, {"depname": "", "version": null, "version_op": null, "unified_name": "", "extractor_type": "ms", "context": "cruppstahl@@upscaledb/win32/msvc2013/lib.vcxproj", "confidence": "High"}, {"depname": "", "version": null, "version_op": null, "unified_name": "", "extractor_type": "ms", "context": "cruppstahl@@upscaledb/win32/msvc2013/lib.vcxproj", "confidence": "High"}, {"depname": "", "version": null, "version_op": null, "unified_name": "", "extractor_type": "ms", "context": "cruppstahl@@upscaledb/win32/msvc2013/lib.vcxproj", "confidence": "High"}, {"depname": "libboost_thread-vc120-mt-1_58", "version": null, "version_op": null, "unified_name": "boost_thread-vc120-mt-1_58", "extractor_type": "ms", "context": "cruppstahl@@upscaledb/win32/msvc2013/lib.vcxproj", "confidence": "High"}, {"depname": "tmp\\libvbyte_x64\\libvbyte", "version": null, "version_op": null, "unified_name": "tmp\\libvbyte_x64\\libvbyte", "extractor_type": "ms", "context": "cruppstahl@@upscaledb/win32/msvc2013/lib.vcxproj", "confidence": "High"}, {"depname": "tmp\\libfor_x64\\libfor", "version": null, "version_op": null, "unified_name": "tmp\\libfor_x64\\libfor", "extractor_type": "ms", "context": "cruppstahl@@upscaledb/win32/msvc2013/lib.vcxproj", "confidence": "High"}, {"depname": "ws2_32", "version": null, "version_op": null, "unified_name": "ws2_32", "extractor_type": "ms", "context": "cruppstahl@@upscaledb/win32/msvc2013/lib.vcxproj", "confidence": "High"}, {"depname": "%(AdditionalDependencies)", "version": null, "version_op": null, "unified_name": "%(additionaldependencies)", "extractor_type": "ms", "context": "cruppstahl@@upscaledb/win32/msvc2013/lib.vcxproj", "confidence": "High"}, {"depname": "Wldap32", "version": null, "version_op": null, "unified_name": "wldap32", "extractor_type": "ms", "context": "cruppstahl@@upscaledb/win32/msvc2013/lib.vcxproj", "confidence": "High"}], "type": "ms"}, {"deps": [], "type": "ms"}, {"deps": [], "type": "ms"}, {"deps": [], "type": "ms"}, {"deps": [], "type": "make"}, {"deps": [], "type": "make"}, {"deps": [], "type": "make"}, {"deps": [], "type": "make"}, {"deps": [], "type": "make"}, {"deps": [{"depname": "simdcomp", "version": "0.0.3", "version_op": null, "unified_name": "simdcomp", "extractor_type": "clib", "context": "cruppstahl@@upscaledb/3rdparty/simdcomp/package.json", "confidence": "High"}], "type": "clib"}, {"deps": [], "type": "make"}, {"deps": [], "type": "make"}, {"deps": [], "type": "make"}, {"deps": [], "type": "make"}, {"deps": [], "type": "make"}, {"deps": [], "type": "make"}, {"deps": [], "type": "make"}, {"deps": [], "type": "make"}, {"deps": [], "type": "make"}, {"deps": [], "type": "make"}, {"deps": [], "type": "make"}, {"deps": [], "type": "make"}, {"deps": [], "type": "make"}, {"deps": [], "type": "make"}, {"deps": [], "type": "make"}, {"deps": [], "type": "make"}, {"deps": [], "type": "make"}, {"deps": [], "type": "make"}, {"deps": [], "type": "make"}, {"deps": [], "type": "make"}]}