{"target": "GStreamer@@gst-rtsp-server", "extractors": [{"deps": [{"depname": "glib-2.0", "version": "2.0", "version_op": null, "unified_name": "glib", "extractor_type": "meson", "context": "GStreamer@@gst-rtsp-server/meson.build", "confidence": "High"}, {"depname": "gstreamer-1.0", "version": "1.0", "version_op": null, "unified_name": "gstreamer", "extractor_type": "meson", "context": "GStreamer@@gst-rtsp-server/meson.build", "confidence": "High"}, {"depname": "gstreamer-rtsp-1.0", "version": "1.0", "version_op": null, "unified_name": "gstreamer-rtsp", "extractor_type": "meson", "context": "GStreamer@@gst-rtsp-server/meson.build", "confidence": "High"}, {"depname": "gstreamer-rtp-1.0", "version": "1.0", "version_op": null, "unified_name": "gstreamer-rtp", "extractor_type": "meson", "context": "GStreamer@@gst-rtsp-server/meson.build", "confidence": "High"}, {"depname": "gstreamer-sdp-1.0", "version": "1.0", "version_op": null, "unified_name": "gstreamer-sdp", "extractor_type": "meson", "context": "GStreamer@@gst-rtsp-server/meson.build", "confidence": "High"}, {"depname": "gstreamer-app-1.0", "version": "1.0", "version_op": null, "unified_name": "gstreamer-app", "extractor_type": "meson", "context": "GStreamer@@gst-rtsp-server/meson.build", "confidence": "High"}, {"depname": "gstreamer-net-1.0", "version": "1.0", "version_op": null, "unified_name": "gstreamer-net", "extractor_type": "meson", "context": "GStreamer@@gst-rtsp-server/meson.build", "confidence": "High"}, {"depname": "gstreamer-check-1.0", "version": "1.0", "version_op": null, "unified_name": "gstreamer-check", "extractor_type": "meson", "context": "GStreamer@@gst-rtsp-server/meson.build", "confidence": "High"}, {"depname": "whichisnotbuiltyet", "version": null, "version_op": null, "unified_name": "whichisnotbuiltyet", "extractor_type": "meson", "context": "GStreamer@@gst-rtsp-server/meson.build", "confidence": "High"}], "type": "meson"}, {"deps": [{"depname": "libcgroup", "version": "0.26", "version_op": ">=", "unified_name": "cgroup", "extractor_type": "meson", "context": "GStreamer@@gst-rtsp-server/examples/meson.build", "confidence": "High"}], "type": "meson"}, {"deps": [], "type": "meson"}, {"deps": [], "type": "meson"}, {"deps": [{"depname": "gstreamer-rtsp-server-1.0", "version": "1.0", "version_op": null, "unified_name": "gstreamer-rtsp-server", "extractor_type": "meson", "context": "GStreamer@@gst-rtsp-server/gst/rtsp-server/meson.build", "confidence": "High"}], "type": "meson"}, {"deps": [], "type": "meson"}, {"deps": [], "type": "meson"}, {"deps": [{"depname": "gstreamer-plugins-base-'+api_version", "version": null, "version_op": null, "unified_name": "gstreamer-plugins-base-'+api_version", "extractor_type": "meson", "context": "GStreamer@@gst-rtsp-server/tests/check/meson.build", "confidence": "High"}, {"depname": "gstreamer-plugins-bad-'+api_version", "version": null, "version_op": null, "unified_name": "gstreamer-plugins-bad-'+api_version", "extractor_type": "meson", "context": "GStreamer@@gst-rtsp-server/tests/check/meson.build", "confidence": "High"}], "type": "meson"}]}