{"target": "lenmus@@lomse", "extractors": [{"deps": [], "type": "cmake", "libs": []}, {"deps": [], "type": "cmake", "libs": []}, {"deps": [], "type": "cmake", "libs": []}, {"deps": [], "type": "cmake", "libs": []}, {"deps": [], "type": "cmake", "libs": []}, {"deps": [{"depname": "unittest++", "version": null, "version_op": null, "unified_name": "unittest++", "extractor_type": "cmake", "context": "find_package(unittest++)", "confidence": "High"}, {"depname": "zlib", "version": null, "version_op": null, "unified_name": "zlib", "extractor_type": "cmake", "context": "find_package(zlib required)", "confidence": "High"}, {"depname": "freetype", "version": null, "version_op": null, "unified_name": "freetype", "extractor_type": "cmake", "context": "find_package(freetype required)", "confidence": "High"}, {"depname": "png", "version": null, "version_op": null, "unified_name": "png", "extractor_type": "cmake", "context": "find_package(png required)", "confidence": "High"}, {"depname": "threads", "version": null, "version_op": null, "unified_name": "threads", "extractor_type": "cmake", "context": "find_package(threads required)", "confidence": "High"}, {"depname": "x11", "version": null, "version_op": null, "unified_name": "x11", "extractor_type": "cmake", "context": "find_package(x11)", "confidence": "High"}, {"depname": "threads", "version": null, "version_op": null, "unified_name": "threads", "extractor_type": "cmake", "context": "find_package (threads)", "confidence": "High"}, {"depname": "lomse", "version": null, "version_op": null, "unified_name": "lomse", "extractor_type": "cmake", "context": "project(lomse)", "confidence": ""}], "type": "cmake", "libs": [{"filenames": ["fontconfig"], "version": "", "fromfile": "lenmus@@lomse/CMakeLists.txt", "content": "find_library(fontconfig_libraries names fontconfig)"}]}, {"deps": [{"depname": "git", "version": null, "version_op": null, "unified_name": "git", "extractor_type": "cmake", "context": "find_package (git)", "confidence": "High"}], "type": "cmake", "libs": []}, {"deps": [{"depname": "cdbs", "version": "", "version_op": null, "unified_name": "cdbs", "extractor_type": "control", "context": "lenmus@@lomse/debian/control", "confidence": "High"}, {"depname": "cmake", "version": "=2.8.10", "version_op": null, "unified_name": "cmake", "extractor_type": "control", "context": "lenmus@@lomse/debian/control", "confidence": "High"}, {"depname": "debhelper", "version": "=8.0.0", "version_op": null, "unified_name": "debhelper", "extractor_type": "control", "context": "lenmus@@lomse/debian/control", "confidence": "High"}, {"depname": "libfontconfig1-dev", "version": "", "version_op": null, "unified_name": "fontconfig1", "extractor_type": "control", "context": "lenmus@@lomse/debian/control", "confidence": "High"}, {"depname": "libfreetype6-dev", "version": "", "version_op": null, "unified_name": "freetype6", "extractor_type": "control", "context": "lenmus@@lomse/debian/control", "confidence": "High"}, {"depname": "libpng++-dev", "version": "", "version_op": null, "unified_name": "png++", "extractor_type": "control", "context": "lenmus@@lomse/debian/control", "confidence": "High"}, {"depname": "pkg-config", "version": "", "version_op": null, "unified_name": "pkg-config", "extractor_type": "control", "context": "lenmus@@lomse/debian/control", "confidence": "High"}, {"depname": "zlib1g", "version": "=1:1.2.1", "version_op": null, "unified_name": "zlib1g", "extractor_type": "control", "context": "lenmus@@lomse/debian/control", "confidence": "High"}, {"depname": "", "version": "", "version_op": null, "unified_name": "", "extractor_type": "control", "context": "lenmus@@lomse/debian/control", "confidence": "High"}], "type": "control"}, {"deps": [{"depname": "unittest++", "version": null, "version_op": null, "unified_name": "unittest++", "extractor_type": "cmake", "context": "lenmus@@lomse/cmake-modules/FindUnitTest++.cmake", "confidence": "High"}], "type": "cmake", "libs": [{"filenames": ["unittest++"], "version": "", "fromfile": "lenmus@@lomse/cmake-modules/FindUnitTest++.cmake", "content": "find_library (unittest++_library\n\tnames\n\t\tunittest++\n\tpaths \n\t\t/usr/lib\n\t\t/usr/local/lib\n\t\t/usr/lib64/ \t\t\n\t\t/sw/lib\n\t\t/opt/local/lib\n\t\t/opt/csw/lib\n\t\t/opt/lib\n\t\t$env{unittest++_dir}/lib\t\t\t\t\t\n\t\t\"c:/program files (x86)/unittest++/lib\"\t\t\n\t\t\"c:/program files/unittest++/lib\"\t\t\t\n)"}]}]}