{"target": "MaJerle@@lwesp", "extractors": [{"deps": [], "type": "gitsubmod"}, {"deps": [{"depname": "lwlibproject", "version": null, "version_op": null, "unified_name": "lwlibproject", "extractor_type": "cmake", "context": "project(lwlibproject)", "confidence": ""}], "type": "cmake", "libs": []}, {"deps": [], "type": "cmake", "libs": []}, {"deps": [], "type": "cmake", "libs": []}, {"deps": [], "type": "ms"}, {"deps": [{"depname": "lwesp_stm32l496g_discovery_netconn_client_rtos", "version": null, "version_op": null, "unified_name": "lwesp_stm32l496g_discovery_netconn_client_rtos", "extractor_type": "cmake", "context": "project(lwesp_stm32l496g_discovery_netconn_client_rtos)", "confidence": ""}], "type": "cmake", "libs": []}, {"deps": [], "type": "cmake", "libs": []}, {"deps": [{"depname": "lwesp_stm32f429zi_nucleo_mqtt_client_api_rtos", "version": null, "version_op": null, "unified_name": "lwesp_stm32f429zi_nucleo_mqtt_client_api_rtos", "extractor_type": "cmake", "context": "project(lwesp_stm32f429zi_nucleo_mqtt_client_api_rtos)", "confidence": ""}], "type": "cmake", "libs": []}, {"deps": [], "type": "cmake", "libs": []}, {"deps": [], "type": "cmake", "libs": []}, {"deps": [{"depname": "lwesp_sntp_rtos", "version": null, "version_op": null, "unified_name": "lwesp_sntp_rtos", "extractor_type": "cmake", "context": "project(lwesp_sntp_rtos)", "confidence": ""}], "type": "cmake", "libs": []}, {"deps": [], "type": "make"}, {"deps": [], "type": "cmake", "libs": []}, {"deps": [], "type": "cmake", "libs": []}]}