{"target": "mindThomas@@Kugle-MATLAB", "extractors": [{"deps": [{"depname": "m", "version": null, "version_op": null, "unified_name": "m", "extractor_type": "make", "context": "mindThomas@@Kugle-MATLAB/Controllers/MPC/generated/kugle_mpc_obstacles_codegen/Makefile:LDLIBS = -lm -lstdc++", "confidence": "High"}, {"depname": "stdc++", "version": null, "version_op": null, "unified_name": "stdc++", "extractor_type": "make", "context": "mindThomas@@Kugle-MATLAB/Controllers/MPC/generated/kugle_mpc_obstacles_codegen/Makefile:LDLIBS = -lm -lstdc++", "confidence": "High"}, {"depname": "rt", "version": null, "version_op": null, "unified_name": "rt", "extractor_type": "make", "context": "mindThomas@@Kugle-MATLAB/Controllers/MPC/generated/kugle_mpc_obstacles_codegen/Makefile:LDLIBS += -lrt", "confidence": "High"}], "type": "make"}, {"deps": [], "type": "make"}, {"deps": [], "type": "make"}, {"deps": [], "type": "make"}, {"deps": [], "type": "make"}, {"deps": [], "type": "make"}]}