{"target": "NFFT@@nfft", "extractors": [{"deps": [{"depname": "NFFT", "version": "NFFT_VERSION", "version_op": null, "unified_name": "nfft", "extractor_type": "autoconf", "context": "AC_INIT([NFFT],[NFFT_VERSION],[mail@nfft.org])", "confidence": ""}, {"depname": "m", "version": null, "version_op": null, "unified_name": "m", "extractor_type": "autoconf", "context": "NFFT@@nfft/configure.ac", "confidence": "High"}], "type": "autoconf"}, {"deps": [], "type": "make"}, {"deps": [], "type": "make"}, {"deps": [], "type": "make"}, {"deps": [], "type": "make"}, {"deps": [], "type": "make"}, {"deps": [], "type": "make"}, {"deps": [], "type": "make"}, {"deps": [], "type": "make"}, {"deps": [], "type": "make"}, {"deps": [], "type": "make"}, {"deps": [], "type": "make"}, {"deps": [], "type": "make"}, {"deps": [], "type": "make"}, {"deps": [], "type": "make"}, {"deps": [], "type": "make"}, {"deps": [], "type": "make"}, {"deps": [], "type": "make"}, {"deps": [], "type": "make"}, {"deps": [], "type": "make"}, {"deps": [], "type": "make"}, {"deps": [], "type": "make"}, {"deps": [], "type": "make"}, {"deps": [], "type": "make"}, {"deps": [], "type": "make"}, {"deps": [], "type": "make"}, {"deps": [], "type": "make"}, {"deps": [], "type": "make"}, {"deps": [], "type": "make"}, {"deps": [], "type": "make"}, {"deps": [], "type": "make"}, {"deps": [], "type": "make"}, {"deps": [], "type": "make"}, {"deps": [], "type": "make"}, {"deps": [], "type": "make"}, {"deps": [], "type": "make"}, {"deps": [], "type": "make"}, {"deps": [], "type": "make"}, {"deps": [], "type": "make"}, {"deps": [], "type": "make"}, {"deps": [], "type": "make"}, {"deps": [], "type": "make"}, {"deps": [], "type": "make"}, {"deps": [], "type": "make"}, {"deps": [], "type": "make"}, {"deps": [], "type": "make"}, {"deps": [], "type": "make"}, {"deps": [], "type": "make"}, {"deps": [], "type": "make"}, {"deps": [], "type": "make"}, {"deps": [], "type": "make"}, {"deps": [], "type": "make"}, {"deps": [], "type": "make"}, {"deps": [], "type": "make"}, {"deps": [], "type": "make"}, {"deps": [], "type": "make"}, {"deps": [], "type": "make"}, {"deps": [], "type": "make"}, {"deps": [], "type": "make"}, {"deps": [], "type": "make"}]}