{"target": "oceancx@@CXEngine", "extractors": [{"deps": [{"depname": "cxengineall", "version": null, "version_op": null, "unified_name": "cxengineall", "extractor_type": "cmake", "context": "project (cxengineall)", "confidence": ""}], "type": "cmake", "libs": []}, {"deps": [], "type": "cmake", "libs": []}, {"deps": [{"depname": "cotire_cmake_module", "version": "1.8.0", "version_op": null, "unified_name": "cotire_cmake_module", "extractor_type": "cmake", "context": "set (cotire_cmake_module_version \"1.8.0\")", "confidence": "Low"}, {"depname": "option_compiler", "version": null, "version_op": null, "unified_name": "option_compiler", "extractor_type": "cmake", "context": "\t\tset (_option_compiler_version \"${cmake_cxx_compiler_version}\")", "confidence": "Low"}, {"depname": "option_compiler", "version": null, "version_op": null, "unified_name": "option_compiler", "extractor_type": "cmake", "context": "\t\tset (_option_compiler_version \"${cmake_cxx_compiler_version}\")", "confidence": "Low"}, {"depname": "option_compiler", "version": null, "version_op": null, "unified_name": "option_compiler", "extractor_type": "cmake", "context": "\t\tset (_option_compiler_version \"${cmake_cxx_compiler_version}\")", "confidence": "Low"}], "type": "cmake", "libs": []}, {"deps": [{"depname": "externals", "version": null, "version_op": null, "unified_name": "externals", "extractor_type": "cmake", "context": "project ( externals  )", "confidence": ""}], "type": "cmake", "libs": []}, {"deps": [{"depname": "cxlua", "version": null, "version_op": null, "unified_name": "cxlua", "extractor_type": "cmake", "context": "find_package(cxlua)", "confidence": "High"}, {"depname": "glew", "version": null, "version_op": null, "unified_name": "glew", "extractor_type": "cmake", "context": "find_package(glew config)", "confidence": "High"}, {"depname": "glfw3", "version": null, "version_op": null, "unified_name": "glfw3", "extractor_type": "cmake", "context": "find_package(glfw3)", "confidence": "High"}, {"depname": "imgui", "version": null, "version_op": null, "unified_name": "imgui", "extractor_type": "cmake", "context": "find_package(imgui)", "confidence": "High"}, {"depname": "cxserver", "version": null, "version_op": null, "unified_name": "cxserver", "extractor_type": "cmake", "context": "project(cxserver)", "confidence": ""}], "type": "cmake", "libs": []}, {"deps": [], "type": "cmake", "libs": []}, {"deps": [{"depname": "cxlua", "version": null, "version_op": null, "unified_name": "cxlua", "extractor_type": "cmake", "context": "find_package(cxlua)", "confidence": "High"}, {"depname": "glew", "version": null, "version_op": null, "unified_name": "glew", "extractor_type": "cmake", "context": "find_package(glew config)", "confidence": "High"}, {"depname": "glfw3", "version": null, "version_op": null, "unified_name": "glfw3", "extractor_type": "cmake", "context": "find_package(glfw3)", "confidence": "High"}, {"depname": "imgui", "version": null, "version_op": null, "unified_name": "imgui", "extractor_type": "cmake", "context": "find_package(imgui)", "confidence": "High"}, {"depname": "cxluax", "version": null, "version_op": null, "unified_name": "cxluax", "extractor_type": "cmake", "context": "project(cxluax)", "confidence": ""}], "type": "cmake", "libs": []}, {"deps": [{"depname": "internals", "version": null, "version_op": null, "unified_name": "internals", "extractor_type": "cmake", "context": "project ( internals  )", "confidence": ""}], "type": "cmake", "libs": []}, {"deps": [{"depname": "cxlua", "version": null, "version_op": null, "unified_name": "cxlua", "extractor_type": "cmake", "context": "find_package(cxlua)", "confidence": "High"}, {"depname": "glew", "version": null, "version_op": null, "unified_name": "glew", "extractor_type": "cmake", "context": "find_package(glew config)", "confidence": "High"}, {"depname": "glfw3", "version": null, "version_op": null, "unified_name": "glfw3", "extractor_type": "cmake", "context": "find_package(glfw3)", "confidence": "High"}, {"depname": "freetype", "version": null, "version_op": null, "unified_name": "freetype", "extractor_type": "cmake", "context": "find_package(freetype config)", "confidence": "High"}, {"depname": "imgui", "version": null, "version_op": null, "unified_name": "imgui", "extractor_type": "cmake", "context": "find_package(imgui)", "confidence": "High"}, {"depname": "gsm", "version": null, "version_op": null, "unified_name": "gsm", "extractor_type": "cmake", "context": "find_package(gsm)", "confidence": "High"}, {"depname": "miniaudio", "version": null, "version_op": null, "unified_name": "miniaudio", "extractor_type": "cmake", "context": "find_package(miniaudio)", "confidence": "High"}, {"depname": "nanovg", "version": null, "version_op": null, "unified_name": "nanovg", "extractor_type": "cmake", "context": "find_package(nanovg)", "confidence": "High"}, {"depname": "cxengine", "version": null, "version_op": null, "unified_name": "cxengine", "extractor_type": "cmake", "context": "project (cxengine languages c cxx)", "confidence": ""}], "type": "cmake", "libs": []}]}