{"target": "XinghaoChen9@@LiveFaceReco_RaspberryPi", "extractors": [{"deps": [{"depname": "opencv", "version": null, "version_op": null, "unified_name": "opencv", "extractor_type": "cmake", "context": "find_package(opencv required)", "confidence": "High"}, {"depname": "openmp", "version": null, "version_op": null, "unified_name": "openmp", "extractor_type": "cmake", "context": "find_package(openmp required)", "confidence": "High"}, {"depname": "livefacereco", "version": null, "version_op": null, "unified_name": "livefacereco", "extractor_type": "cmake", "context": "project(livefacereco)", "confidence": ""}], "type": "cmake", "libs": []}, {"deps": [], "type": "cmake", "libs": []}, {"deps": [], "type": "cmake", "libs": []}, {"deps": [{"depname": "facerecognizer", "version": null, "version_op": null, "unified_name": "facerecognizer", "extractor_type": "cmake", "context": "project(facerecognizer)", "confidence": ""}], "type": "cmake", "libs": []}, {"deps": [{"depname": "livefacereco", "version": null, "version_op": null, "unified_name": "livefacereco", "extractor_type": "cmake", "context": "project(livefacereco)", "confidence": ""}], "type": "cmake", "libs": []}]}